{
    "Group":  "GRS_SSW45-2022",
    "SiteSource":  "https://grs2.ekmd.huji.ac.il/home/schoolofsocialwork/SSW45-2022/external_forms",
    "SiteDest":  "https://grs2.ekmd.huji.ac.il/home/schoolofsocialwork/SSW37-2021/external_forms/",
    "List":  "Final",
    "PermDifference":  "GRS_SSW45-2022_JUDGESUG;GRS_SSW45-2022_JUDGESSP;",
    "PermSource":  [
                       {
                           "Name":  "ekccUG",
                           "Type":  4,
                           "PermissionLevels":  "Full Control"
                       },
                       {
                           "Name":  "GRS_SSW45-2022_adminUG",
                           "Type":  4,
                           "PermissionLevels":  "Full Control"
                       },
                       {
                           "Name":  "System Account",
                           "Type":  1,
                           "PermissionLevels":  "Full Control"
                       }
                   ],
    "PermDest":  [
                     {
                         "Name":  "ekccUG",
                         "Type":  4,
                         "PermissionLevels":  "Full Control"
                     },
                     {
                         "Name":  "GRS_SSW45-2022_adminUG",
                         "Type":  4,
                         "PermissionLevels":  "Full Control"
                     },
                     {
                         "Name":  "System Account",
                         "Type":  1,
                         "PermissionLevels":  "Full Control"
                     }
                 ]
}
