{
    "Group":  "GRS_EDU60-2021",
    "SiteSource":  "https://grs.ekmd.huji.ac.il/home/Education/EDU60-2021",
    "SiteDest":  "https://grs2.ekmd.huji.ac.il/home/Education/EDU57-2021/",
    "List":  "סוג מסלול",
    "PermDifference":  "GRS_EDU60-2021_JUDGESUG;",
    "PermSource":  [
                       {
                           "Name":  "EKMD\\all_apps_grpsug",
                           "Type":  4,
                           "PermissionLevels":  "Read"
                       },
                       {
                           "Name":  "ekccUG",
                           "Type":  4,
                           "PermissionLevels":  "Full Control"
                       },
                       {
                           "Name":  "GRS_EDU60-2021_adminUG",
                           "Type":  4,
                           "PermissionLevels":  "Full Control,Limited Access"
                       },
                       {
                           "Name":  "GRS_EDU60-2021_adminSP",
                           "Type":  8,
                           "PermissionLevels":  "Read"
                       },
                       {
                           "Name":  "GRS_EDU60-2021_judgesSP",
                           "Type":  8,
                           "PermissionLevels":  "Read"
                       },
                       {
                           "Name":  "System Account",
                           "Type":  1,
                           "PermissionLevels":  "Full Control,Limited Access"
                       }
                   ],
    "PermDest":  [
                     {
                         "Name":  "EKMD\\all_apps_grpsug",
                         "Type":  4,
                         "PermissionLevels":  "Read"
                     },
                     {
                         "Name":  "ekccUG",
                         "Type":  4,
                         "PermissionLevels":  "Full Control"
                     },
                     {
                         "Name":  "GRS_EDU60-2021_adminUG",
                         "Type":  4,
                         "PermissionLevels":  "Full Control,Limited Access"
                     },
                     {
                         "Name":  "GRS_EDU60-2021_adminSP",
                         "Type":  8,
                         "PermissionLevels":  "Read"
                     },
                     {
                         "Name":  "GRS_EDU60-2021_judgesSP",
                         "Type":  8,
                         "PermissionLevels":  "Read"
                     },
                     {
                         "Name":  "System Account",
                         "Type":  1,
                         "PermissionLevels":  "Full Control,Limited Access"
                     }
                 ]
}
