{
    "Group":  "HSS_GEN157-2021",
    "SiteSource":  "https://scholarships.ekmd.huji.ac.il/home/General/GEN157-2021",
    "SiteDest":  "https://scholarships2.ekmd.huji.ac.il/home/General/GEN142-2020/",
    "List":  "DocType",
    "PermDifference":  "HSS_GEN157-2021_ADMINSP;HSS_GEN157-2021_JUDGESSP;",
    "PermSource":  [
                       {
                           "Name":  "ekccUG",
                           "Type":  4,
                           "PermissionLevels":  "Full Control"
                       },
                       {
                           "Name":  "EKMD\\all_apps_grpsug",
                           "Type":  4,
                           "PermissionLevels":  "Read"
                       },
                       {
                           "Name":  "HSS_GEN157-2021_adminUG",
                           "Type":  4,
                           "PermissionLevels":  "Full Control"
                       },
                       {
                           "Name":  "System Account",
                           "Type":  1,
                           "PermissionLevels":  "Full Control"
                       }
                   ],
    "PermDest":  [
                     {
                         "Name":  "ekccUG",
                         "Type":  4,
                         "PermissionLevels":  "Full Control"
                     },
                     {
                         "Name":  "EKMD\\all_apps_grpsug",
                         "Type":  4,
                         "PermissionLevels":  "Read"
                     },
                     {
                         "Name":  "HSS_GEN157-2021_adminUG",
                         "Type":  4,
                         "PermissionLevels":  "Full Control"
                     },
                     {
                         "Name":  "System Account",
                         "Type":  1,
                         "PermissionLevels":  "Full Control"
                     }
                 ]
}
