[
    {
        "URL":  "https://scholarships.ekmd.huji.ac.il/home/General/GEN156-2021",
        "Deadline":  "\/Date(1641247264000)\/",
        "Lang":  "En"
    },
    {
        "URL":  "https://scholarships.ekmd.huji.ac.il/home/Agriculture/AGR160-2021",
        "Deadline":  "\/Date(1641679271000)\/",
        "Lang":  "EN(HE)"
    },
    {
        "URL":  "https://scholarships.ekmd.huji.ac.il/home/Agriculture/AGR162-2021",
        "Deadline":  "\/Date(1641679265000)\/",
        "Lang":  "EN(HE)"
    },
    {
        "URL":  "https://scholarships.ekmd.huji.ac.il/home/Humanities/HUM175-2021",
        "Deadline":  "\/Date(1641420064000)\/",
        "Lang":  "En"
    },
    {
        "URL":  "https://scholarships.ekmd.huji.ac.il/home/SocialSciences/SOC212-2021",
        "Deadline":  "\/Date(1642197664000)\/",
        "Lang":  "He"
    },
    {
        "URL":  "https://scholarships.ekmd.huji.ac.il/home/General/GEN157-2021",
        "Deadline":  "\/Date(1641679200000)\/",
        "Lang":  "En"
    },
    {
        "URL":  "https://scholarships.ekmd.huji.ac.il/home/SchoolofSocialWork/SSW38-2021",
        "Deadline":  "\/Date(1642370400000)\/",
        "Lang":  "He"
    },
    {
        "URL":  "https://scholarships.ekmd.huji.ac.il/home/SchoolofSocialWork/SSW51-2021",
        "Deadline":  "\/Date(1642370400000)\/",
        "Lang":  "He"
    },
    {
        "URL":  "https://scholarships.ekmd.huji.ac.il/home/SchoolofSocialWork/SSW52-2021",
        "Deadline":  "\/Date(1642370400000)\/",
        "Lang":  "He"
    },
    {
        "URL":  "https://scholarships.ekmd.huji.ac.il/home/Humanities/HUM182-2021",
        "Deadline":  "\/Date(1641938400000)\/",
        "Lang":  "EN(HE)"
    },
    {
        "URL":  "https://scholarships.ekmd.huji.ac.il/home/General/GEN158-2021",
        "Deadline":  "\/Date(1644184800000)\/",
        "Lang":  "En"
    },
    {
        "URL":  "https://scholarships.ekmd.huji.ac.il/home/NaturalScience/SCI75-2021",
        "Deadline":  "\/Date(1643580000000)\/",
        "Lang":  "He"
    },
    {
        "URL":  "https://scholarships.ekmd.huji.ac.il/home/SchoolofSocialWork/SSW54-2021",
        "Deadline":  "\/Date(1642629667000)\/",
        "Lang":  null
    },
    {
        "URL":  "https://scholarships.ekmd.huji.ac.il/home/SocialSciences/SOC215-2021",
        "Deadline":  "\/Date(1646517600000)\/",
        "Lang":  "He"
    },
    {
        "URL":  "https://scholarships.ekmd.huji.ac.il/home/Agriculture/AGR167-2021",
        "Deadline":  "\/Date(1644703200000)\/",
        "Lang":  "He"
    },
    {
        "URL":  "https://scholarships.ekmd.huji.ac.il/home/SchoolofSocialWork/SSW55-2021",
        "Deadline":  "\/Date(1641679200000)\/",
        "Lang":  "He"
    },
    {
        "URL":  "https://scholarships.ekmd.huji.ac.il/home/SocialSciences/SOC217-2021",
        "Deadline":  "\/Date(1642888800000)\/",
        "Lang":  "He"
    },
    {
        "URL":  "https://scholarships.ekmd.huji.ac.il/home/BUS/BUS11-2019",
        "Deadline":  "\/Date(1643666400000)\/",
        "Lang":  "He"
    },
    {
        "URL":  "https://scholarships.ekmd.huji.ac.il/home/Education/EDU127-2021",
        "Deadline":  "\/Date(1662066000000)\/",
        "Lang":  "He"
    },
    {
        "URL":  "https://scholarships.ekmd.huji.ac.il/home/SchoolofSocialWork/SSW56-2021",
        "Deadline":  "\/Date(1664658000000)\/",
        "Lang":  "He"
    },
    {
        "URL":  "https://scholarships.ekmd.huji.ac.il/home/Education/EDU128-2021",
        "Deadline":  "\/Date(1642024800000)\/",
        "Lang":  "He"
    },
    {
        "URL":  "https://scholarships.ekmd.huji.ac.il/home/Education/EDU129-2021",
        "Deadline":  "\/Date(1644357600000)\/",
        "Lang":  "He"
    }
]
